llama_index/postprocessor/xinference_rerank/__init__.py
llama_index/postprocessor/xinference_rerank/base.py
llama_index_postprocessor_xinference_rerank-0.3.1.dist-info/METADATA
llama_index_postprocessor_xinference_rerank-0.3.1.dist-info/WHEEL
llama_index_postprocessor_xinference_rerank-0.3.1.dist-info/licenses/LICENSE
llama_index_postprocessor_xinference_rerank-0.3.1.dist-info/RECORD
